higgsbacktesting/AlphaStockBacktesting.py
higgsbacktesting/CFSingleInstrumentStrategy.py
higgsbacktesting/CFTimetoTicklabel.py
higgsbacktesting/GTASingleStockStrategy.py
higgsbacktesting/GTATimetoTicklabel.py
higgsbacktesting/SingleInstrumentStrategy.py
higgsbacktesting/__init__.py
higgsbacktest-0.1.0.dist-info/LICENSE
higgsbacktest-0.1.0.dist-info/METADATA
higgsbacktest-0.1.0.dist-info/WHEEL
higgsbacktest-0.1.0.dist-info/top_level.txt
higgsbacktest-0.1.0.dist-info/RECORD
